libmdtoc/__init__.py
mdtoc/__init__.py
md_toc_creator-1.4.1.dist-info/LICENSE
md_toc_creator-1.4.1.dist-info/METADATA
md_toc_creator-1.4.1.dist-info/WHEEL
md_toc_creator-1.4.1.dist-info/entry_points.txt
md_toc_creator-1.4.1.dist-info/top_level.txt
md_toc_creator-1.4.1.dist-info/RECORD
