Metadata-Version: 2.1
Name: md-toc-creator
Version: 1.4.1
Summary: Generates a table of contents for a markdown document in markdown.
Home-page: https://github.com/mcb2003/md-toc-creator
Author: Michael Connor Buchan
Author-email: mikeybuchan@hotmail.co.uk
License: UNKNOWN
Platform: UNKNOWN
Classifier: Programming Language :: Python :: 3
Classifier: License :: OSI Approved :: GNU General Public License v3 or later (GPLv3+)
Classifier: Environment :: Console
Classifier: Operating System :: OS Independent
Classifier: Development Status :: 5 - Production/Stable
Classifier: Intended Audience :: Developers
Classifier: Natural Language :: English
Classifier: Topic :: Text Processing :: Markup
Classifier: Topic :: Text Editors :: Text Processing
